package com.tencent.mapapi.map;

public final class al
{
  private String TX = "";

  public al(String paramString)
  {
    this.TX = bq.b(paramString);
  }

  // ERROR //
  public final java.lang.Integer mG()
  {
    // Byte code:
    //   0: aload_0
    //   1: getfield 15	com/tencent/mapapi/map/al:TX	Ljava/lang/String;
    //   4: invokestatic 35	com/tencent/mapapi/a/b:mj	()Ljava/lang/String;
    //   7: invokestatic 41	com/tencent/a/a/a:h	(Ljava/lang/String;Ljava/lang/String;)Lcom/tencent/a/a/c;
    //   10: astore_2
    //   11: aload_2
    //   12: ifnull +10 -> 22
    //   15: aload_2
    //   16: getfield 47	com/tencent/a/a/c:data	[B
    //   19: ifnonnull +5 -> 24
    //   22: aconst_null
    //   23: areturn
    //   24: aload_2
    //   25: getfield 50	com/tencent/a/a/c:XZ	Ljava/lang/String;
    //   28: astore_3
    //   29: aload_2
    //   30: getfield 47	com/tencent/a/a/c:data	[B
    //   33: astore 4
    //   35: new 52	java/lang/String
    //   38: dup
    //   39: aload 4
    //   41: aload_3
    //   42: invokespecial 55	java/lang/String:<init>	([BLjava/lang/String;)V
    //   45: astore 5
    //   47: new 57	org/json/JSONObject
    //   50: dup
    //   51: aload 5
    //   53: invokespecial 59	org/json/JSONObject:<init>	(Ljava/lang/String;)V
    //   56: astore 6
    //   58: aload 6
    //   60: ldc 61
    //   62: invokevirtual 65	org/json/JSONObject:getJSONObject	(Ljava/lang/String;)Lorg/json/JSONObject;
    //   65: astore 8
    //   67: aload 8
    //   69: ldc 67
    //   71: invokevirtual 71	org/json/JSONObject:getInt	(Ljava/lang/String;)I
    //   74: istore 10
    //   76: iload 10
    //   78: invokestatic 77	java/lang/Integer:valueOf	(I)Ljava/lang/Integer;
    //   81: areturn
    //   82: astore 12
    //   84: aconst_null
    //   85: astore 5
    //   87: goto -40 -> 47
    //   90: astore 9
    //   92: aconst_null
    //   93: areturn
    //   94: astore 7
    //   96: aconst_null
    //   97: areturn
    //   98: astore 11
    //   100: aconst_null
    //   101: areturn
    //   102: astore_1
    //   103: aconst_null
    //   104: areturn
    //
    // Exception table:
    //   from	to	target	type
    //   35	47	82	java/io/UnsupportedEncodingException
    //   67	76	90	org/json/JSONException
    //   58	67	94	org/json/JSONException
    //   47	58	98	org/json/JSONException
    //   0	11	102	java/lang/Exception
  }
}

/* Location:           /Users/don/Desktop/mm/com.tencent.mm/classes-dex2jar.jar
 * Qualified Name:     com.tencent.mapapi.map.al
 * JD-Core Version:    0.6.2
 */