package com.tencent.mm.ui.tools;

import com.tencent.mm.ui.base.cc;

final class gr
  implements cc
{
  gr(WebViewUI paramWebViewUI)
  {
  }

  // ERROR //
  public final void a(com.tencent.mm.ui.base.bx parambx)
  {
    // Byte code:
    //   0: aload_0
    //   1: getfield 12	com/tencent/mm/ui/tools/gr:hnv	Lcom/tencent/mm/ui/tools/WebViewUI;
    //   4: invokestatic 24	com/tencent/mm/ui/tools/WebViewUI:a	(Lcom/tencent/mm/ui/tools/WebViewUI;)Lcom/tencent/mm/ui/tools/gb;
    //   7: invokevirtual 30	com/tencent/mm/ui/tools/gb:aNQ	()Lcom/tencent/mm/protocal/JsapiPermissionWrapper;
    //   10: astore_2
    //   11: aload_2
    //   12: invokevirtual 36	com/tencent/mm/protocal/JsapiPermissionWrapper:awe	()Z
    //   15: ifeq +22 -> 37
    //   18: aload_1
    //   19: iconst_1
    //   20: aload_0
    //   21: getfield 12	com/tencent/mm/ui/tools/gr:hnv	Lcom/tencent/mm/ui/tools/WebViewUI;
    //   24: getstatic 42	com/tencent/mm/n:buy	I
    //   27: invokevirtual 46	com/tencent/mm/ui/tools/WebViewUI:getString	(I)Ljava/lang/String;
    //   30: getstatic 51	com/tencent/mm/h:agK	I
    //   33: invokevirtual 56	com/tencent/mm/ui/base/bx:a	(ILjava/lang/CharSequence;I)Landroid/view/MenuItem;
    //   36: pop
    //   37: aload_2
    //   38: invokevirtual 59	com/tencent/mm/protocal/JsapiPermissionWrapper:awg	()Z
    //   41: ifeq +22 -> 63
    //   44: aload_1
    //   45: iconst_2
    //   46: aload_0
    //   47: getfield 12	com/tencent/mm/ui/tools/gr:hnv	Lcom/tencent/mm/ui/tools/WebViewUI;
    //   50: getstatic 62	com/tencent/mm/n:buz	I
    //   53: invokevirtual 46	com/tencent/mm/ui/tools/WebViewUI:getString	(I)Ljava/lang/String;
    //   56: getstatic 65	com/tencent/mm/h:agF	I
    //   59: invokevirtual 56	com/tencent/mm/ui/base/bx:a	(ILjava/lang/CharSequence;I)Landroid/view/MenuItem;
    //   62: pop
    //   63: aload_0
    //   64: getfield 12	com/tencent/mm/ui/tools/gr:hnv	Lcom/tencent/mm/ui/tools/WebViewUI;
    //   67: invokestatic 69	com/tencent/mm/ui/tools/WebViewUI:v	(Lcom/tencent/mm/ui/tools/WebViewUI;)Z
    //   70: ifne +32 -> 102
    //   73: aload_0
    //   74: getfield 12	com/tencent/mm/ui/tools/gr:hnv	Lcom/tencent/mm/ui/tools/WebViewUI;
    //   77: invokestatic 72	com/tencent/mm/ui/tools/WebViewUI:w	(Lcom/tencent/mm/ui/tools/WebViewUI;)Z
    //   80: ifeq +22 -> 102
    //   83: aload_1
    //   84: iconst_3
    //   85: aload_0
    //   86: getfield 12	com/tencent/mm/ui/tools/gr:hnv	Lcom/tencent/mm/ui/tools/WebViewUI;
    //   89: getstatic 75	com/tencent/mm/n:bsu	I
    //   92: invokevirtual 46	com/tencent/mm/ui/tools/WebViewUI:getString	(I)Ljava/lang/String;
    //   95: getstatic 78	com/tencent/mm/h:agu	I
    //   98: invokevirtual 56	com/tencent/mm/ui/base/bx:a	(ILjava/lang/CharSequence;I)Landroid/view/MenuItem;
    //   101: pop
    //   102: aload_2
    //   103: invokevirtual 81	com/tencent/mm/protocal/JsapiPermissionWrapper:awf	()Z
    //   106: ifeq +22 -> 128
    //   109: aload_1
    //   110: iconst_4
    //   111: aload_0
    //   112: getfield 12	com/tencent/mm/ui/tools/gr:hnv	Lcom/tencent/mm/ui/tools/WebViewUI;
    //   115: getstatic 84	com/tencent/mm/n:buA	I
    //   118: invokevirtual 46	com/tencent/mm/ui/tools/WebViewUI:getString	(I)Ljava/lang/String;
    //   121: getstatic 87	com/tencent/mm/h:agM	I
    //   124: invokevirtual 56	com/tencent/mm/ui/base/bx:a	(ILjava/lang/CharSequence;I)Landroid/view/MenuItem;
    //   127: pop
    //   128: aload_0
    //   129: getfield 12	com/tencent/mm/ui/tools/gr:hnv	Lcom/tencent/mm/ui/tools/WebViewUI;
    //   132: invokevirtual 91	com/tencent/mm/ui/tools/WebViewUI:getIntent	()Landroid/content/Intent;
    //   135: ldc 93
    //   137: invokevirtual 99	android/content/Intent:getStringExtra	(Ljava/lang/String;)Ljava/lang/String;
    //   140: astore_3
    //   141: aload_3
    //   142: invokestatic 105	com/tencent/mm/sdk/platformtools/cj:hX	(Ljava/lang/String;)Z
    //   145: ifne +66 -> 211
    //   148: aload_0
    //   149: getfield 12	com/tencent/mm/ui/tools/gr:hnv	Lcom/tencent/mm/ui/tools/WebViewUI;
    //   152: getfield 109	com/tencent/mm/ui/tools/WebViewUI:cOg	Lcom/tencent/mm/plugin/webview/stub/al;
    //   155: aload_3
    //   156: invokeinterface 114 2 0
    //   161: istore 22
    //   163: iload 22
    //   165: istore 18
    //   167: iload 18
    //   169: ifeq +386 -> 555
    //   172: aload_2
    //   173: invokevirtual 117	com/tencent/mm/protocal/JsapiPermissionWrapper:awc	()Z
    //   176: istore 19
    //   178: iload 19
    //   180: ifeq +31 -> 211
    //   183: iload 18
    //   185: ifeq +379 -> 564
    //   188: getstatic 120	com/tencent/mm/n:bIj	I
    //   191: istore 20
    //   193: aload_1
    //   194: iconst_5
    //   195: aload_0
    //   196: getfield 12	com/tencent/mm/ui/tools/gr:hnv	Lcom/tencent/mm/ui/tools/WebViewUI;
    //   199: iload 20
    //   201: invokevirtual 46	com/tencent/mm/ui/tools/WebViewUI:getString	(I)Ljava/lang/String;
    //   204: getstatic 123	com/tencent/mm/h:agI	I
    //   207: invokevirtual 56	com/tencent/mm/ui/base/bx:a	(ILjava/lang/CharSequence;I)Landroid/view/MenuItem;
    //   210: pop
    //   211: aload_2
    //   212: invokevirtual 126	com/tencent/mm/protocal/JsapiPermissionWrapper:awb	()Z
    //   215: ifeq +23 -> 238
    //   218: aload_1
    //   219: bipush 11
    //   221: aload_0
    //   222: getfield 12	com/tencent/mm/ui/tools/gr:hnv	Lcom/tencent/mm/ui/tools/WebViewUI;
    //   225: getstatic 129	com/tencent/mm/n:bux	I
    //   228: invokevirtual 46	com/tencent/mm/ui/tools/WebViewUI:getString	(I)Ljava/lang/String;
    //   231: getstatic 132	com/tencent/mm/h:agy	I
    //   234: invokevirtual 56	com/tencent/mm/ui/base/bx:a	(ILjava/lang/CharSequence;I)Landroid/view/MenuItem;
    //   237: pop
    //   238: aload_2
    //   239: invokevirtual 135	com/tencent/mm/protocal/JsapiPermissionWrapper:aww	()Z
    //   242: ifeq +23 -> 265
    //   245: aload_1
    //   246: bipush 6
    //   248: aload_0
    //   249: getfield 12	com/tencent/mm/ui/tools/gr:hnv	Lcom/tencent/mm/ui/tools/WebViewUI;
    //   252: getstatic 138	com/tencent/mm/n:bHY	I
    //   255: invokevirtual 46	com/tencent/mm/ui/tools/WebViewUI:getString	(I)Ljava/lang/String;
    //   258: getstatic 141	com/tencent/mm/h:agG	I
    //   261: invokevirtual 56	com/tencent/mm/ui/base/bx:a	(ILjava/lang/CharSequence;I)Landroid/view/MenuItem;
    //   264: pop
    //   265: aload_2
    //   266: invokevirtual 144	com/tencent/mm/protocal/JsapiPermissionWrapper:awx	()Z
    //   269: ifeq +23 -> 292
    //   272: aload_1
    //   273: bipush 7
    //   275: aload_0
    //   276: getfield 12	com/tencent/mm/ui/tools/gr:hnv	Lcom/tencent/mm/ui/tools/WebViewUI;
    //   279: getstatic 147	com/tencent/mm/n:bId	I
    //   282: invokevirtual 46	com/tencent/mm/ui/tools/WebViewUI:getString	(I)Ljava/lang/String;
    //   285: getstatic 150	com/tencent/mm/h:agt	I
    //   288: invokevirtual 56	com/tencent/mm/ui/base/bx:a	(ILjava/lang/CharSequence;I)Landroid/view/MenuItem;
    //   291: pop
    //   292: aload_2
    //   293: invokevirtual 153	com/tencent/mm/protocal/JsapiPermissionWrapper:awp	()Z
    //   296: ifeq +49 -> 345
    //   299: aload_0
    //   300: getfield 12	com/tencent/mm/ui/tools/gr:hnv	Lcom/tencent/mm/ui/tools/WebViewUI;
    //   303: getfield 109	com/tencent/mm/ui/tools/WebViewUI:cOg	Lcom/tencent/mm/plugin/webview/stub/al;
    //   306: invokeinterface 157 1 0
    //   311: astore 13
    //   313: aload 13
    //   315: astore 11
    //   317: aload 11
    //   319: invokestatic 105	com/tencent/mm/sdk/platformtools/cj:hX	(Ljava/lang/String;)Z
    //   322: ifne +250 -> 572
    //   325: aload_1
    //   326: bipush 8
    //   328: aload_0
    //   329: getfield 12	com/tencent/mm/ui/tools/gr:hnv	Lcom/tencent/mm/ui/tools/WebViewUI;
    //   332: getstatic 160	com/tencent/mm/n:bIf	I
    //   335: invokevirtual 46	com/tencent/mm/ui/tools/WebViewUI:getString	(I)Ljava/lang/String;
    //   338: getstatic 163	com/tencent/mm/h:agC	I
    //   341: invokevirtual 56	com/tencent/mm/ui/base/bx:a	(ILjava/lang/CharSequence;I)Landroid/view/MenuItem;
    //   344: pop
    //   345: aload_0
    //   346: getfield 12	com/tencent/mm/ui/tools/gr:hnv	Lcom/tencent/mm/ui/tools/WebViewUI;
    //   349: invokestatic 69	com/tencent/mm/ui/tools/WebViewUI:v	(Lcom/tencent/mm/ui/tools/WebViewUI;)Z
    //   352: ifeq +33 -> 385
    //   355: aload_0
    //   356: getfield 12	com/tencent/mm/ui/tools/gr:hnv	Lcom/tencent/mm/ui/tools/WebViewUI;
    //   359: invokestatic 72	com/tencent/mm/ui/tools/WebViewUI:w	(Lcom/tencent/mm/ui/tools/WebViewUI;)Z
    //   362: ifeq +23 -> 385
    //   365: aload_1
    //   366: bipush 9
    //   368: aload_0
    //   369: getfield 12	com/tencent/mm/ui/tools/gr:hnv	Lcom/tencent/mm/ui/tools/WebViewUI;
    //   372: getstatic 166	com/tencent/mm/n:bdx	I
    //   375: invokevirtual 46	com/tencent/mm/ui/tools/WebViewUI:getString	(I)Ljava/lang/String;
    //   378: getstatic 169	com/tencent/mm/h:agv	I
    //   381: invokevirtual 56	com/tencent/mm/ui/base/bx:a	(ILjava/lang/CharSequence;I)Landroid/view/MenuItem;
    //   384: pop
    //   385: aload_0
    //   386: getfield 12	com/tencent/mm/ui/tools/gr:hnv	Lcom/tencent/mm/ui/tools/WebViewUI;
    //   389: invokestatic 24	com/tencent/mm/ui/tools/WebViewUI:a	(Lcom/tencent/mm/ui/tools/WebViewUI;)Lcom/tencent/mm/ui/tools/gb;
    //   392: invokevirtual 173	com/tencent/mm/ui/tools/gb:aNR	()Lcom/tencent/mm/protocal/GeneralControlWrapper;
    //   395: invokevirtual 178	com/tencent/mm/protocal/GeneralControlWrapper:avG	()Z
    //   398: ifeq +23 -> 421
    //   401: aload_1
    //   402: bipush 10
    //   404: aload_0
    //   405: getfield 12	com/tencent/mm/ui/tools/gr:hnv	Lcom/tencent/mm/ui/tools/WebViewUI;
    //   408: getstatic 181	com/tencent/mm/n:bfY	I
    //   411: invokevirtual 46	com/tencent/mm/ui/tools/WebViewUI:getString	(I)Ljava/lang/String;
    //   414: getstatic 184	com/tencent/mm/h:agJ	I
    //   417: invokevirtual 56	com/tencent/mm/ui/base/bx:a	(ILjava/lang/CharSequence;I)Landroid/view/MenuItem;
    //   420: pop
    //   421: aload_2
    //   422: invokevirtual 187	com/tencent/mm/protocal/JsapiPermissionWrapper:awv	()Z
    //   425: ifeq +96 -> 521
    //   428: aload_0
    //   429: getfield 12	com/tencent/mm/ui/tools/gr:hnv	Lcom/tencent/mm/ui/tools/WebViewUI;
    //   432: getfield 109	com/tencent/mm/ui/tools/WebViewUI:cOg	Lcom/tencent/mm/plugin/webview/stub/al;
    //   435: invokeinterface 190 1 0
    //   440: ifeq +81 -> 521
    //   443: aload_0
    //   444: getfield 12	com/tencent/mm/ui/tools/gr:hnv	Lcom/tencent/mm/ui/tools/WebViewUI;
    //   447: getfield 109	com/tencent/mm/ui/tools/WebViewUI:cOg	Lcom/tencent/mm/plugin/webview/stub/al;
    //   450: invokeinterface 194 1 0
    //   455: astore 5
    //   457: aload 5
    //   459: invokeinterface 200 1 0
    //   464: astore 6
    //   466: aload 6
    //   468: invokeinterface 205 1 0
    //   473: ifeq +109 -> 582
    //   476: aload_1
    //   477: aload 6
    //   479: invokeinterface 209 1 0
    //   484: checkcast 211	java/lang/String
    //   487: invokevirtual 215	com/tencent/mm/ui/base/bx:add	(Ljava/lang/CharSequence;)Landroid/view/MenuItem;
    //   490: pop
    //   491: goto -25 -> 466
    //   494: astore 4
    //   496: ldc 217
    //   498: new 219	java/lang/StringBuilder
    //   501: dup
    //   502: ldc 221
    //   504: invokespecial 224	java/lang/StringBuilder:<init>	(Ljava/lang/String;)V
    //   507: aload 4
    //   509: invokevirtual 227	java/lang/Exception:getMessage	()Ljava/lang/String;
    //   512: invokevirtual 231	java/lang/StringBuilder:append	(Ljava/lang/String;)Ljava/lang/StringBuilder;
    //   515: invokevirtual 234	java/lang/StringBuilder:toString	()Ljava/lang/String;
    //   518: invokestatic 239	com/tencent/mm/sdk/platformtools/aa:w	(Ljava/lang/String;Ljava/lang/String;)V
    //   521: return
    //   522: astore 17
    //   524: ldc 217
    //   526: new 219	java/lang/StringBuilder
    //   529: dup
    //   530: ldc 241
    //   532: invokespecial 224	java/lang/StringBuilder:<init>	(Ljava/lang/String;)V
    //   535: aload 17
    //   537: invokevirtual 227	java/lang/Exception:getMessage	()Ljava/lang/String;
    //   540: invokevirtual 231	java/lang/StringBuilder:append	(Ljava/lang/String;)Ljava/lang/StringBuilder;
    //   543: invokevirtual 234	java/lang/StringBuilder:toString	()Ljava/lang/String;
    //   546: invokestatic 244	com/tencent/mm/sdk/platformtools/aa:e	(Ljava/lang/String;Ljava/lang/String;)V
    //   549: iconst_0
    //   550: istore 18
    //   552: goto -385 -> 167
    //   555: aload_2
    //   556: invokevirtual 247	com/tencent/mm/protocal/JsapiPermissionWrapper:awd	()Z
    //   559: istore 19
    //   561: goto -383 -> 178
    //   564: getstatic 250	com/tencent/mm/n:bIa	I
    //   567: istore 20
    //   569: goto -376 -> 193
    //   572: ldc 217
    //   574: ldc 252
    //   576: invokestatic 255	com/tencent/mm/sdk/platformtools/aa:i	(Ljava/lang/String;Ljava/lang/String;)V
    //   579: goto -234 -> 345
    //   582: aload_0
    //   583: getfield 12	com/tencent/mm/ui/tools/gr:hnv	Lcom/tencent/mm/ui/tools/WebViewUI;
    //   586: aload 5
    //   588: invokestatic 258	com/tencent/mm/ui/tools/WebViewUI:a	(Lcom/tencent/mm/ui/tools/WebViewUI;Ljava/util/List;)V
    //   591: return
    //   592: astore 10
    //   594: aconst_null
    //   595: astore 11
    //   597: goto -280 -> 317
    //
    // Exception table:
    //   from	to	target	type
    //   421	466	494	java/lang/Exception
    //   466	491	494	java/lang/Exception
    //   582	591	494	java/lang/Exception
    //   148	163	522	java/lang/Exception
    //   299	313	592	java/lang/Exception
  }
}

/* Location:           /Users/don/Desktop/mm/com.tencent.mm/classes-dex2jar.jar
 * Qualified Name:     com.tencent.mm.ui.tools.gr
 * JD-Core Version:    0.6.2
 */